[
    {
        "key": "dbln",
        "value": "%7B%2261567124442745%22%3A%22Wh8NSwuy%22%2C%2261568397839667%22%3A%22cIRENBkS%22%7D",
        "domain": "facebook.com",
        "path": "/login/device-based/",
        "hostOnly": false,
        "creation": "2024-12-02T07:23:47.539Z",
        "lastAccessed": "2024-12-02T07:23:47.539Z"
    },
    {
        "key": "sb",
        "value": "JDcXZ5k4zT9hMF0oxUkBSSMO",
        "domain": "facebook.com",
        "path": "/",
        "hostOnly": false,
        "creation": "2024-12-02T07:23:47.539Z",
        "lastAccessed": "2024-12-02T07:23:47.539Z"
    },
    {
        "key": "datr",
        "value": "-oJBZ0wVJyfVp5Vo6DZPf0Uc",
        "domain": "facebook.com",
        "path": "/",
        "hostOnly": false,
        "creation": "2024-12-02T07:23:47.539Z",
        "lastAccessed": "2024-12-02T07:23:47.539Z"
    },
    {
        "key": "ps_l",
        "value": "1",
        "domain": "facebook.com",
        "path": "/",
        "hostOnly": false,
        "creation": "2024-12-02T07:23:47.540Z",
        "lastAccessed": "2024-12-02T07:23:47.540Z"
    },
    {
        "key": "ps_n",
        "value": "1",
        "domain": "facebook.com",
        "path": "/",
        "hostOnly": false,
        "creation": "2024-12-02T07:23:47.540Z",
        "lastAccessed": "2024-12-02T07:23:47.540Z"
    },
    {
        "key": "dpr",
        "value": "4.288609504699707",
        "domain": "facebook.com",
        "path": "/",
        "hostOnly": false,
        "creation": "2024-12-02T07:23:47.540Z",
        "lastAccessed": "2024-12-02T07:23:47.540Z"
    },
    {
        "key": "vpd",
        "value": "v1%3B492x277x3.9006972312927246",
        "domain": "facebook.com",
        "path": "/",
        "hostOnly": false,
        "creation": "2024-12-02T07:23:47.540Z",
        "lastAccessed": "2024-12-02T07:23:47.540Z"
    },
    {
        "key": "locale",
        "value": "en_US",
        "domain": "facebook.com",
        "path": "/",
        "hostOnly": false,
        "creation": "2024-12-02T07:23:47.540Z",
        "lastAccessed": "2024-12-02T07:23:47.540Z"
    },
    {
        "key": "c_user",
        "value": "100091832567860",
        "domain": "facebook.com",
        "path": "/",
        "hostOnly": false,
        "creation": "2024-12-02T07:23:47.540Z",
        "lastAccessed": "2024-12-02T07:23:47.540Z"
    },
    {
        "key": "wd",
        "value": "320x569",
        "domain": "facebook.com",
        "path": "/",
        "hostOnly": false,
        "creation": "2024-12-02T07:23:47.540Z",
        "lastAccessed": "2024-12-02T07:23:47.540Z"
    },
    {
        "key": "presence",
        "value": "C%7B%22t3%22%3A%5B%5D%2C%22utc3%22%3A1733124149163%2C%22v%22%3A1%7D",
        "domain": "facebook.com",
        "path": "/",
        "hostOnly": false,
        "creation": "2024-12-02T07:23:47.540Z",
        "lastAccessed": "2024-12-02T07:23:47.540Z"
    },
    {
        "key": "fr",
        "value": "16HkWN3zcytRPE0N5.AWUHAT5goUKcxIqWBDYDRS9NJaA.BnTWA1..AAA.0.0.BnTWA1.AWWUjZG9RQ0",
        "domain": "facebook.com",
        "path": "/",
        "hostOnly": false,
        "creation": "2024-12-02T07:23:47.540Z",
        "lastAccessed": "2024-12-02T07:23:47.540Z"
    },
    {
        "key": "xs",
        "value": "35%3ATsdgFOH1CYQEFw%3A2%3A1733112552%3A-1%3A14769%3A%3AAcVSEaReRnrhlHXPCbCoy_d8n68Q2FT46sUGSwtlrg",
        "domain": "facebook.com",
        "path": "/",
        "hostOnly": false,
        "creation": "2024-12-02T07:23:47.540Z",
        "lastAccessed": "2024-12-02T07:23:47.540Z"
    },
    {
        "key": "fbl_st",
        "value": "101623490%3BT%3A28885403",
        "domain": "facebook.com",
        "path": "/",
        "hostOnly": false,
        "creation": "2024-12-02T07:23:47.540Z",
        "lastAccessed": "2024-12-02T07:23:47.540Z"
    },
    {
        "key": "wl_cbv",
        "value": "v2%3Bclient_version%3A2682%3Btimestamp%3A1733124199",
        "domain": "facebook.com",
        "path": "/",
        "hostOnly": false,
        "creation": "2024-12-02T07:23:47.540Z",
        "lastAccessed": "2024-12-02T07:23:47.540Z"
    }
        ]
